falconpb/__init__.py
falconpb/falconpb.py
falconpb-1.0.0.dist-info/DESCRIPTION.rst
falconpb-1.0.0.dist-info/METADATA
falconpb-1.0.0.dist-info/metadata.json
falconpb-1.0.0.dist-info/RECORD
falconpb-1.0.0.dist-info/top_level.txt
falconpb-1.0.0.dist-info/WHEEL
