Metadata-Version: 2.0
Name: falconpb
Version: 1.0.0
Summary: Protocol Buffers based resource for Falcon
Home-page: http://github.com/5amfung/falconpb
Author: Sam Fung
Author-email: sam.fung@gmail.com
License: UNKNOWN
Keywords: falcon protocol buffers protobuf
Platform: UNKNOWN
Classifier: Programming Language :: Python :: 2.6
Classifier: Programming Language :: Python :: 2.7
Classifier: Intended Audience :: Developers
Classifier: Topic :: Software Development :: Libraries :: Python Modules
Requires-Dist: falcon (>=0.2)
Requires-Dist: protobuf-to-dict (>=0.1.0)
